README
setup.py
natural/__init__.py
natural/bank.py
natural/constant.py
natural/data.py
natural/date.py
natural/file.py
natural/language.py
natural/number.py
natural/phone.py
natural/size.py
natural/text.py
natural/util.py
natural/locale/af_ZA/LC_MESSAGES/natural.mo
natural/locale/de_DE/LC_MESSAGES/natural.mo
natural/locale/en_GB/LC_MESSAGES/natural.mo
natural/locale/en_US/LC_MESSAGES/natural.mo
natural/locale/es_ES/LC_MESSAGES/natural.mo
natural/locale/fr_FR/LC_MESSAGES/natural.mo
natural/locale/ja_JP/LC_MESSAGES/natural.mo
natural/locale/nl_NL/LC_MESSAGES/natural.mo
natural3.egg-info/PKG-INFO
natural3.egg-info/SOURCES.txt
natural3.egg-info/dependency_links.txt
natural3.egg-info/pbr.json
natural3.egg-info/requires.txt
natural3.egg-info/top_level.txt