Metadata-Version: 1.0
Name: natural3
Version: 0.1.6
Summary: Convert data to their natural (human-readable) format (fork for py3k support)
Home-page: https://github.com/tehmaze/natural
Author: Wijnand Modderman-Lenstra
Author-email: maze@pyth0n.org
License: MIT
Keywords: natural data date file number size
Platform: UNKNOWN
